inventory_viewer/__init__.py
inventory_viewer/navigation.py
inventory_viewer/tables.py
inventory_viewer/urls.py
inventory_viewer/views.py
inventory_viewer/templates/inventory_viewer/inventory_view.html
inventory_viewer-1.0.1.dist-info/licenses/LICENSE
inventory_viewer-1.0.1.dist-info/METADATA
inventory_viewer-1.0.1.dist-info/WHEEL
inventory_viewer-1.0.1.dist-info/top_level.txt
inventory_viewer-1.0.1.dist-info/RECORD
